odoo/addons/ssi_project/README.rst
odoo/addons/ssi_project/__init__.py
odoo/addons/ssi_project/__manifest__.py
odoo/addons/ssi_project/menu.xml
odoo/addons/ssi_project/approval_template/project_deliverable.xml
odoo/addons/ssi_project/approval_template/project_phase.xml
odoo/addons/ssi_project/base_automation/project_delivarable.xml
odoo/addons/ssi_project/base_automation/project_phase.xml
odoo/addons/ssi_project/i18n/ssi_project.pot
odoo/addons/ssi_project/ir_action_server/project_deliverable.xml
odoo/addons/ssi_project/ir_action_server/project_phase.xml
odoo/addons/ssi_project/ir_sequence/project_deliverable.xml
odoo/addons/ssi_project/ir_sequence/project_phase.xml
odoo/addons/ssi_project/models/__init__.py
odoo/addons/ssi_project/models/project_deliverable.py
odoo/addons/ssi_project/models/project_deliverable_type.py
odoo/addons/ssi_project/models/project_deliverable_type_category.py
odoo/addons/ssi_project/models/project_milestone.py
odoo/addons/ssi_project/models/project_phase.py
odoo/addons/ssi_project/models/project_project.py
odoo/addons/ssi_project/models/project_task.py
odoo/addons/ssi_project/models/project_task_type.py
odoo/addons/ssi_project/models/task_dependency.py
odoo/addons/ssi_project/models/task_instruction.py
odoo/addons/ssi_project/policy_template/project_deliverable.xml
odoo/addons/ssi_project/policy_template/project_phase.xml
odoo/addons/ssi_project/security/ir.model.access.csv
odoo/addons/ssi_project/security/ir_model_access_data.xml
odoo/addons/ssi_project/security/ir_module_category_data.xml
odoo/addons/ssi_project/security/ir_rule_data.xml
odoo/addons/ssi_project/security/res_group_data.xml
odoo/addons/ssi_project/security/ir_model_access/project_deliverable.xml
odoo/addons/ssi_project/security/ir_model_access/project_phase.xml
odoo/addons/ssi_project/security/ir_module_category/project_deliverable.xml
odoo/addons/ssi_project/security/ir_module_category/project_phase.xml
odoo/addons/ssi_project/security/ir_rule/project_deliverable.xml
odoo14_addon_ssi_project-14.0.3.6.0.dist-info/METADATA
odoo14_addon_ssi_project-14.0.3.6.0.dist-info/WHEEL
odoo14_addon_ssi_project-14.0.3.6.0.dist-info/top_level.txt
odoo14_addon_ssi_project-14.0.3.6.0.dist-info/RECORD
